faketrumpgen
