Metadata-Version: 1.0
Name: faketrumpgen
Version: 0.11
Summary: Fake trump facebook post generator
Home-page: https://github.com/maxcaron/faketrumpgen
Author: Maxime Caron
Author-email: maximecaron@live.fr
License: MIT
Platform: UNKNOWN
